autolycus/__init__.py
autolycus/hg2git.py
autolycus/hg_fast_export.py
autolycus/hg_reset.py
autolycus/legacy.py
autolycus/sync.py
autolycus/sh/hg-fast-export.sh
autolycus/sh/hg-reset.sh
autolycus-0.0.7.dist-info/DESCRIPTION.rst
autolycus-0.0.7.dist-info/entry_points.txt
autolycus-0.0.7.dist-info/METADATA
autolycus-0.0.7.dist-info/metadata.json
autolycus-0.0.7.dist-info/RECORD
autolycus-0.0.7.dist-info/top_level.txt
autolycus-0.0.7.dist-info/WHEEL
