Metadata-Version: 2.0
Name: autolycus
Version: 0.0.7
Summary: Exports/synchronizes a Mercurial repo to Git
Home-page: http://github.com/nicktimko/autolycus
Author: Nick Timkovich
Author-email: prometheus235@gmail.com
License: GPLv2
Keywords: mercurial git vcs dvcs
Platform: UNKNOWN
Classifier: Development Status :: 3 - Alpha
Classifier: Programming Language :: Python :: 2 :: Only
Classifier: Programming Language :: Python :: 2.7
Classifier: Topic :: Utilities
Classifier: License :: OSI Approved :: GNU General Public License v2 (GPLv2)
Requires-Dist: mercurial
